aider_follama/__init__.py
aider_follama/aider_runner.py
aider_follama/api_server.py
aider_follama/cli.py
aider_follama/db_logger.py
aider_follama/model_connector.py
aider_follama/rag_pipeline.py
aider_follama/rag_runner.py
aider_rag-0.1.3.dist-info/METADATA
aider_rag-0.1.3.dist-info/WHEEL
aider_rag-0.1.3.dist-info/entry_points.txt
aider_rag-0.1.3.dist-info/top_level.txt
aider_rag-0.1.3.dist-info/RECORD
