Metadata-Version: 2.1
Name: aider-rag
Version: 0.1.3
Requires-Dist: aider-chat
Requires-Dist: langchain
Requires-Dist: faiss-cpu
Requires-Dist: openai
Requires-Dist: tiktoken
Requires-Dist: transformers
Requires-Dist: sentence-transformers
Requires-Dist: Flask
Requires-Dist: SQLAlchemy==2.0.41
Requires-Dist: pysqlite3
